practica4paq/primo.py
practica4paq-0.1.dist-info/LICENSE.txt
practica4paq-0.1.dist-info/METADATA
practica4paq-0.1.dist-info/WHEEL
practica4paq-0.1.dist-info/top_level.txt
practica4paq-0.1.dist-info/RECORD
